sentrifyai-0.1.7-py3.10-nspkg.pth
sentrifyai/api.py
sentrifyai/config.py
sentrifyai/exceptions.py
sentrifyai-0.1.7.dist-info/LICENSE
sentrifyai-0.1.7.dist-info/METADATA
sentrifyai-0.1.7.dist-info/WHEEL
sentrifyai-0.1.7.dist-info/namespace_packages.txt
sentrifyai-0.1.7.dist-info/top_level.txt
sentrifyai-0.1.7.dist-info/RECORD
