Metadata-Version: 2.1
Name: sentrifyai
Version: 0.1.7
Summary: SentrifyAI API client
Home-page: https://github.com/sentrifybot/sentrifyai-python
Author: SentrifyAI
Author-email: admin@sentrify.org
Classifier: Programming Language :: Python :: 3
Classifier: License :: OSI Approved :: MIT License
Classifier: Operating System :: OS Independent
Requires-Python: >=3.6
License-File: LICENSE
Requires-Dist: requests
